amwater/__init__.py
amwater/amwater.py
amwater-0.0.3.dist-info/LICENSE
amwater-0.0.3.dist-info/METADATA
amwater-0.0.3.dist-info/WHEEL
amwater-0.0.3.dist-info/entry_points.txt
amwater-0.0.3.dist-info/top_level.txt
amwater-0.0.3.dist-info/RECORD
