Metadata-Version: 2.1
Name: amwater
Version: 0.0.3
Summary: Alert CLI for American water
Home-page: https://github.com/samapriya/amwater
Author: Samapriya Roy
Author-email: samapriya.roy@gmail.com
License: Apache 2.0
Platform: UNKNOWN
Classifier: Intended Audience :: Developers
Classifier: Intended Audience :: Science/Research
Classifier: Natural Language :: English
Classifier: License :: OSI Approved :: MIT License
Classifier: Programming Language :: Python :: 3.6
Classifier: Programming Language :: Python :: 3.7
Classifier: Operating System :: OS Independent
Classifier: Topic :: Scientific/Engineering :: GIS
Requires-Dist: requests (>=2.26.0)
Requires-Dist: lxml (>=4.6.3)
Requires-Dist: beautifulsoup4 (>=4.9.3)
Requires-Dist: dateparser (>=1.0.0)
Requires-Dist: shapely (>=1.6.4) ; platform_system != "Windows"
